[
    {
        "ranking": "1",
        "title": "Sana Güvenmiyorum - Dedub Sessions",
        "artist": "Dedublüman, Aleyna Tilki",
        "image": "https://i.scdn.co/image/ab67616d00001e02586d3ac510fd1220ecfb97eb",
        "peak": "1",
        "prev": "1",
        "streak": "10",
        "streams": "1,130,299",
        "spotifyID": "1lNcnIU4jtqD69Qtfjh8EJ"
    },
    {
        "ranking": "2",
        "title": "Italy Forma",
        "artist": "Ati242",
        "image": "https://i.scdn.co/image/ab67616d00001e0279dbe6c33d218de4aa59223b",
        "peak": "1",
        "prev": "2",
        "streak": "31",
        "streams": "699,731",
        "spotifyID": "7FfdTwI2i0b5PNeNvqtqCY"
    },
    {
        "ranking": "3",
        "title": "Canın Beni Çekti",
        "artist": "Melike Şahin",
        "image": "https://i.scdn.co/image/ab67616d00001e02a4c00daa19d544b7bd9e78cc",
        "peak": "1",
        "prev": "3",
        "streak": "46",
        "streams": "629,037",
        "spotifyID": "1UIznGFIwNUKUza5kJ9f2G"
    },
    {
        "ranking": "4",
        "title": "CISTAK",
        "artist": "Era7capone, Batuflex, Narco",
        "image": "https://i.scdn.co/image/ab67616d00001e02f0d10a31b96e69a21cf09399",
        "peak": "1",
        "prev": "4",
        "streak": "45",
        "streams": "587,847",
        "spotifyID": "0K791kh3oLkBD5KVWg1LJ8"
    },
    {
        "ranking": "5",
        "title": "SEVMEYİ DENEMEDİN",
        "artist": "BLOK3",
        "image": "https://i.scdn.co/image/ab67616d00001e028f9028a4726d40fb8c8e0b44",
        "peak": "1",
        "prev": "5",
        "streak": "58",
        "streams": "507,040",
        "spotifyID": "3ff93VTp2DBbNnDEsAW8Cm"
    },
    {
        "ranking": "6",
        "title": "GELME İSTEMEM",
        "artist": "BLOK3",
        "image": "https://i.scdn.co/image/ab67616d00001e02e5d14853d53bf463763334cd",
        "peak": "4",
        "prev": "6",
        "streak": "10",
        "streams": "483,695",
        "spotifyID": "2X4NUYZN0ylbM41ADKYv1X"
    },
    {
        "ranking": "7",
        "title": "Değişmene Rağmen",
        "artist": "Ati242",
        "image": "https://i.scdn.co/image/ab67616d00001e0279dbe6c33d218de4aa59223b",
        "peak": "1",
        "prev": "7",
        "streak": "129",
        "streams": "435,847",
        "spotifyID": "5pEpvR03HbLxkBtK73EeJw"
    },
    {
        "ranking": "8",
        "title": "Yasemen",
        "artist": "Afra",
        "image": "https://i.scdn.co/image/ab67616d00001e021a0ed0646427c873335a002d",
        "peak": "1",
        "prev": "8",
        "streak": "37",
        "streams": "392,137",
        "spotifyID": "2SVoUZdzxuDuxBdHSO73KF"
    },
    {
        "ranking": "9",
        "title": "İNTİHAR",
        "artist": "Era7capone, NASTEISHA",
        "image": "https://i.scdn.co/image/ab67616d00001e0221b7a0b0d2e44706336b71e2",
        "peak": "3",
        "prev": "13",
        "streak": "149",
        "streams": "357,822",
        "spotifyID": "0osZ5jmtTtHJt8pPz6RL2N"
    },
    {
        "ranking": "10",
        "title": "Onlar Anlamaz Halden",
        "artist": "Semicenk",
        "image": "https://i.scdn.co/image/ab67616d00001e02dc4721fefe12a86355da4fed",
        "peak": "2",
        "prev": "10",
        "streak": "93",
        "streams": "356,947",
        "spotifyID": "38d47UiHhyu4wdbPYz0ZUB"
    },
    {
        "ranking": "11",
        "title": "Düşmez Kalkmaz",
        "artist": "Canbay & Wolker",
        "image": "https://i.scdn.co/image/ab67616d00001e02bd18be70bed43633c15476f0",
        "peak": "9",
        "prev": "12",
        "streak": "74",
        "streams": "349,201",
        "spotifyID": "57w7FOfLpXZ9GWlAooYrSK"
    },
    {
        "ranking": "12",
        "title": "OF OF OF",
        "artist": "ElMusto, Organize",
        "image": "https://i.scdn.co/image/ab67616d00001e02cac09830b781702ad6eceb00",
        "peak": "4",
        "prev": "15",
        "streak": "107",
        "streams": "346,669",
        "spotifyID": "1RI3YE0BqwN2Fd6Ej0gTqW"
    },
    {
        "ranking": "13",
        "title": "Geçiyor Zaman",
        "artist": "Semicenk",
        "image": "https://i.scdn.co/image/ab67616d00001e02dc4721fefe12a86355da4fed",
        "peak": "2",
        "prev": "9",
        "streak": "93",
        "streams": "346,486",
        "spotifyID": "3ma4Ef3Bnl3UBOV4ShiMLX"
    },
    {
        "ranking": "14",
        "title": "Saygımdan",
        "artist": "Bengü",
        "image": "https://i.scdn.co/image/ab67616d00001e0297ad00a32edde479dfa03c8b",
        "peak": "13",
        "prev": "14",
        "streak": "110",
        "streams": "329,702",
        "spotifyID": "4E10qEzOmTIVmrg6Wz2RHj"
    },
    {
        "ranking": "15",
        "title": "Sen Bilmezsin",
        "artist": "Dedublüman",
        "image": "https://i.scdn.co/image/ab67616d00001e02b428d70d3d9e11a61101b10d",
        "peak": "5",
        "prev": "11",
        "streak": "240",
        "streams": "313,341",
        "spotifyID": "5VykLQtjCYF6qFq59HbUg9"
    },
    {
        "ranking": "16",
        "title": "25",
        "artist": "Ati242",
        "image": "https://i.scdn.co/image/ab67616d00001e0208caa6d45ef97ce44edf1189",
        "peak": "10",
        "prev": "17",
        "streak": "827",
        "streams": "309,350",
        "spotifyID": "4HuB9A0O1XwmwTVtTgODm8"
    },
    {
        "ranking": "17",
        "title": "Önümüz Yaz",
        "artist": "Simge",
        "image": "https://i.scdn.co/image/ab67616d00001e027276e8ccef1536051f7033db",
        "peak": "2",
        "prev": "21",
        "streak": "142",
        "streams": "305,396",
        "spotifyID": "28Aau4tlztDlgKJQXrWhZR"
    },
    {
        "ranking": "18",
        "title": "Bunca Yıl - Dedub Sessions",
        "artist": "Dedublüman, Can Kazaz",
        "image": "https://i.scdn.co/image/ab67616d00001e02af8f33ec834cc43b161e204f",
        "peak": "1",
        "prev": "18",
        "streak": "51",
        "streams": "298,066",
        "spotifyID": "0mSFwDtiAPPNwBOSFnI3G5"
    },
    {
        "ranking": "19",
        "title": "Duydun Mu?",
        "artist": "Yusuf Güney",
        "image": "https://i.scdn.co/image/ab67616d00001e02b5c1238d9c7bd190ab1a1b27",
        "peak": "12",
        "prev": "16",
        "streak": "29",
        "streams": "294,745",
        "spotifyID": "4v8LZr4pYJFo3lnB5BJBAc"
    },
    {
        "ranking": "20",
        "title": "Telefon",
        "artist": "Ati242",
        "image": "https://i.scdn.co/image/ab67616d00001e0279dbe6c33d218de4aa59223b",
        "peak": "12",
        "prev": "19",
        "streak": "132",
        "streams": "291,702",
        "spotifyID": "1kfXupjpLLLwSkzebqZT2X"
    },
    {
        "ranking": "21",
        "title": "Kalbim Yanımda",
        "artist": "Ati242",
        "image": "https://i.scdn.co/image/ab67616d00001e0279dbe6c33d218de4aa59223b",
        "peak": "13",
        "prev": "22",
        "streak": "133",
        "streams": "281,799",
        "spotifyID": "3Lpeu0zbUXY1WfoGy1vEuh"
    },
    {
        "ranking": "22",
        "title": "PİŞT",
        "artist": "Era7capone",
        "image": "https://i.scdn.co/image/ab67616d00001e020e8cc935be12c1759d017849",
        "peak": "13",
        "prev": "23",
        "streak": "37",
        "streams": "280,147",
        "spotifyID": "2ugG3itPOpM9IANApt473B"
    },
    {
        "ranking": "23",
        "title": "Düğün Dernek",
        "artist": "Jeff Redd",
        "image": "https://i.scdn.co/image/ab67616d00001e021b25b6fa654556479a22e23d",
        "peak": "9",
        "prev": "28",
        "streak": "89",
        "streams": "272,051",
        "spotifyID": "6dQJfND64RJy6xJQMsc3ij"
    },
    {
        "ranking": "24",
        "title": "ESC*BAR",
        "artist": "BLOK3",
        "image": "https://i.scdn.co/image/ab67616d00001e028f9028a4726d40fb8c8e0b44",
        "peak": "3",
        "prev": "24",
        "streak": "128",
        "streams": "260,420",
        "spotifyID": "7JVUP1J9urt49OdiFbWGeZ"
    },
    {
        "ranking": "25",
        "title": "Tırnağın Kırılmasın",
        "artist": "Emir Can İğrek",
        "image": "https://i.scdn.co/image/ab67616d00001e029fb44af51a251074720f7489",
        "peak": "12",
        "prev": "20",
        "streak": "9",
        "streams": "259,536",
        "spotifyID": "36SKXwHlE1zYin3xwPRDnU"
    },
    {
        "ranking": "26",
        "title": "Beni Hatırla",
        "artist": "Nazan Öncel",
        "image": "https://i.scdn.co/image/ab67616d00001e020b82bbdfde15d431b6140034",
        "peak": "14",
        "prev": "29",
        "streak": "132",
        "streams": "249,793",
        "spotifyID": "4mwKj8jNSq8eTp3ylpcBAE"
    },
    {
        "ranking": "27",
        "title": "Kaptan",
        "artist": "Ati242",
        "image": "https://i.scdn.co/image/ab67616d00001e0279dbe6c33d218de4aa59223b",
        "peak": "4",
        "prev": "30",
        "streak": "219",
        "streams": "247,921",
        "spotifyID": "1JcYQfCTP7qXC4F8AO0h9W"
    },
    {
        "ranking": "28",
        "title": "Sönen Sigaralar",
        "artist": "Ati242",
        "image": "https://i.scdn.co/image/ab67616d00001e0279dbe6c33d218de4aa59223b",
        "peak": "8",
        "prev": "27",
        "streak": "31",
        "streams": "245,317",
        "spotifyID": "0QuKutgaaa0Q1WUZEnrZ93"
    },
    {
        "ranking": "29",
        "title": "Halbuki",
        "artist": "Yalın",
        "image": "https://i.scdn.co/image/ab67616d00001e025a725cb5e31c8a34cec0d956",
        "peak": "6",
        "prev": "26",
        "streak": "80",
        "streams": "244,737",
        "spotifyID": "5RZH849e1ZWa2qeVz6O3mK"
    },
    {
        "ranking": "30",
        "title": "Dale Don Dale",
        "artist": "ElMusto",
        "image": "https://i.scdn.co/image/ab67616d00001e02393fe1aa705fe9d486155849",
        "peak": "1",
        "prev": "35",
        "streak": "96",
        "streams": "242,376",
        "spotifyID": "1f9X5YDmXDxyIwhzB06JJd"
    },
    {
        "ranking": "31",
        "title": "Ait Hissetmiyorum",
        "artist": "Ati242",
        "image": "https://i.scdn.co/image/ab67616d00001e0279dbe6c33d218de4aa59223b",
        "peak": "6",
        "prev": "25",
        "streak": "31",
        "streams": "232,996",
        "spotifyID": "5XQ1eD5Esz1CzdjH9bzbzn"
    },
    {
        "ranking": "32",
        "title": "Küle Dönmüşsün",
        "artist": "Semicenk, Doğu Swag",
        "image": "https://i.scdn.co/image/ab67616d00001e02d6186badad09b9caeefb80a1",
        "peak": "2",
        "prev": "32",
        "streak": "149",
        "streams": "231,675",
        "spotifyID": "2CZzw0He9fzyi2FkBkn4Bk"
    },
    {
        "ranking": "33",
        "title": "Uzaktan",
        "artist": "Göksel",
        "image": "https://i.scdn.co/image/ab67616d00001e02eb4534ca1227f529d3895fd1",
        "peak": "26",
        "prev": "45",
        "streak": "89",
        "streams": "221,658",
        "spotifyID": "1TxvnXbTRmYwtlkFEn8Rpb"
    },
    {
        "ranking": "34",
        "title": "ÇÖZEMEZLER",
        "artist": "Lvbel C5, AKDO",
        "image": "https://i.scdn.co/image/ab67616d00001e02b654ca2e4b043fce4f5ed085",
        "peak": "15",
        "prev": "41",
        "streak": "69",
        "streams": "221,509",
        "spotifyID": "300xFtOH49F80uB7BSAsEf"
    },
    {
        "ranking": "35",
        "title": "aklına ben gelicem",
        "artist": "BLOK3",
        "image": "https://i.scdn.co/image/ab67616d00001e027a63255a1952dbb456bf3b9a",
        "peak": "1",
        "prev": "31",
        "streak": "416",
        "streams": "218,104",
        "spotifyID": "3ZwRkdnTb4az8X5n4WXuHA"
    },
    {
        "ranking": "36",
        "title": "Ortak",
        "artist": "Melike Şahin",
        "image": "https://i.scdn.co/image/ab67616d00001e02a4c00daa19d544b7bd9e78cc",
        "peak": "17",
        "prev": "33",
        "streak": "100",
        "streams": "209,453",
        "spotifyID": "6naElV4AFSUQfwb84K7TB4"
    },
    {
        "ranking": "37",
        "title": "Bertaraf",
        "artist": "Canbay & Wolker, Heijan, Muti",
        "image": "https://i.scdn.co/image/ab67616d00001e0202e24f5c665c050841304a1b",
        "peak": "4",
        "prev": "34",
        "streak": "408",
        "streams": "207,354",
        "spotifyID": "1PiyTtoNn0m4kfJWLfjHny"
    },
    {
        "ranking": "38",
        "title": "Maybach",
        "artist": "Ati242",
        "image": "https://i.scdn.co/image/ab67616d00001e0279dbe6c33d218de4aa59223b",
        "peak": "7",
        "prev": "36",
        "streak": "31",
        "streams": "205,802",
        "spotifyID": "2j7M9A1Ko4LHi46sAmgLSF"
    },
    {
        "ranking": "39",
        "title": "Aradan Çok Yıllar Geçti",
        "artist": "Tuğçe Kandemir",
        "image": "https://i.scdn.co/image/ab67616d00001e029049f9a6b1b62df39848031d",
        "peak": "3",
        "prev": "40",
        "streak": "119",
        "streams": "204,373",
        "spotifyID": "4CDY8eGMrkQjyOTkvsXiq0"
    },
    {
        "ranking": "40",
        "title": "ILTIMAS X SUBMARINER",
        "artist": "AKDO, Gülşen, Murat Boz, Lvbel C5",
        "image": "https://i.scdn.co/image/ab67616d00001e02bf0353b496e117582b4e2970",
        "peak": "3",
        "prev": "49",
        "streak": "179",
        "streams": "201,321",
        "spotifyID": "1ppnRAPv8zJjrNy4TW5w7M"
    },
    {
        "ranking": "41",
        "title": "Naçar",
        "artist": "Emre Fel",
        "image": "https://i.scdn.co/image/ab67616d00001e021ed0f3097e59ccf5c2eeec91",
        "peak": "6",
        "prev": "38",
        "streak": "58",
        "streams": "198,497",
        "spotifyID": "6Abw6zEw0EbfFC6OJob4Ph"
    },
    {
        "ranking": "42",
        "title": "Sakladığın Bir Şeyler Var",
        "artist": "Dedublüman",
        "image": "https://i.scdn.co/image/ab67616d00001e029b7b7dacc44acdcafb69a1a2",
        "peak": "18",
        "prev": "44",
        "streak": "777",
        "streams": "196,837",
        "spotifyID": "6t18CcJVpnFAoWfcZxiZtk"
    },
    {
        "ranking": "43",
        "title": "Durma Yürüsene",
        "artist": "Melike Şahin",
        "image": "https://i.scdn.co/image/ab67616d00001e02a4c00daa19d544b7bd9e78cc",
        "peak": "32",
        "prev": "37",
        "streak": "104",
        "streams": "196,676",
        "spotifyID": "2up5kUpA2yQb5DtXE8B2WJ"
    },
    {
        "ranking": "44",
        "title": "Yankı",
        "artist": "Simge",
        "image": "https://i.scdn.co/image/ab67616d00001e0292b6c0333ee123e9ff1bf5b4",
        "peak": "32",
        "prev": "51",
        "streak": "52",
        "streams": "188,684",
        "spotifyID": "4y3QBJf9E8yDJCEFbRK8xk"
    },
    {
        "ranking": "45",
        "title": "Intro",
        "artist": "Ati242",
        "image": "https://i.scdn.co/image/ab67616d00001e0279dbe6c33d218de4aa59223b",
        "peak": "17",
        "prev": "39",
        "streak": "31",
        "streams": "185,591",
        "spotifyID": "0JMJAump4huv3wtiNxRbTx"
    },
    {
        "ranking": "46",
        "title": "Neyleyim İstanbulu",
        "artist": "Murat Dalkılıç",
        "image": "https://i.scdn.co/image/ab67616d00001e0282ffa31dbb0212d91c096d12",
        "peak": "32",
        "prev": "48",
        "streak": "78",
        "streams": "183,886",
        "spotifyID": "4tMqaNjQxHsWpYORQ7renT"
    },
    {
        "ranking": "47",
        "title": "La La La",
        "artist": "Jeff Redd",
        "image": "https://i.scdn.co/image/ab67616d00001e0241f141964d0e124ea5cefbc2",
        "peak": "20",
        "prev": "46",
        "streak": "79",
        "streams": "182,675",
        "spotifyID": "3blRKhNNedjdZFR0b9Wtxw"
    },
    {
        "ranking": "48",
        "title": "VURDUM TELLERİNE",
        "artist": "M Lisa",
        "image": "https://i.scdn.co/image/ab67616d00001e0279b32776a856f29831c0f02f",
        "peak": "37",
        "prev": "43",
        "streak": "28",
        "streams": "180,345",
        "spotifyID": "5Y5fFEqazjbtNAgbx9noTF"
    },
    {
        "ranking": "49",
        "title": "APT.",
        "artist": "ROSÉ, Bruno Mars",
        "image": "https://i.scdn.co/image/ab67616d00001e0259639b3440e708daa35987be",
        "peak": "17",
        "prev": "57",
        "streak": "23",
        "streams": "178,479",
        "spotifyID": "5vNRhkKd0yEAg8suGBpjeY"
    },
    {
        "ranking": "50",
        "title": "Bir Karanfil",
        "artist": "Emir Can İğrek",
        "image": "https://i.scdn.co/image/ab67616d00001e02716e1f060e72f24c29f86a5f",
        "peak": "13",
        "prev": "54",
        "streak": "156",
        "streams": "178,475",
        "spotifyID": "0a56Y5XrlRQ0JYg6jse5QJ"
    },
    {
        "ranking": "51",
        "title": "Dilerim Ki",
        "artist": "Dolu Kadehi Ters Tut",
        "image": "https://i.scdn.co/image/ab67616d00001e029410959ab7f05d8216da799d",
        "peak": "29",
        "prev": "50",
        "streak": "303",
        "streams": "177,378",
        "spotifyID": "6cjIlxXM1ca6nxkJ0p27jU"
    },
    {
        "ranking": "52",
        "title": "Yarasalar",
        "artist": "Ati242",
        "image": "https://i.scdn.co/image/ab67616d00001e0279dbe6c33d218de4aa59223b",
        "peak": "11",
        "prev": "47",
        "streak": "31",
        "streams": "175,668",
        "spotifyID": "7rB7UrKvW1yfFEiRrZsrXt"
    },
    {
        "ranking": "53",
        "title": "nE !?",
        "artist": "Lvbel C5",
        "image": "https://i.scdn.co/image/ab67616d00001e02bde27f666d136d4c7e6e71a9",
        "peak": "5",
        "prev": "55",
        "streak": "212",
        "streams": "175,371",
        "spotifyID": "1Ma4fLShd0hpZSNH37mEkR"
    },
    {
        "ranking": "54",
        "title": "Kumralım",
        "artist": "Yaşar",
        "image": "https://i.scdn.co/image/ab67616d00001e02d6652ff2755bedbda0914b35",
        "peak": "30",
        "prev": "64",
        "streak": "627",
        "streams": "171,166",
        "spotifyID": "3tCCD2qQLdC99YkRwGPSsx"
    },
    {
        "ranking": "55",
        "title": "Kabul Olan Tek Duamsın",
        "artist": "Shawty",
        "image": "https://i.scdn.co/image/ab67616d00001e02d6691f652bba76d6135af49e",
        "peak": "6",
        "prev": "52",
        "streak": "90",
        "streams": "170,970",
        "spotifyID": "36oBlwSPNtA48TLYqk4SNp"
    },
    {
        "ranking": "56",
        "title": "Ölüyorum Anla",
        "artist": "Mert Demir",
        "image": "https://i.scdn.co/image/ab67616d00001e02b43e827a90ff9800414211c0",
        "peak": "4",
        "prev": "56",
        "streak": "135",
        "streams": "170,478",
        "spotifyID": "7AxK6ojozGBLlxuRaXwQQ1"
    },
    {
        "ranking": "57",
        "title": "Hikaye Bitti Çoktan",
        "artist": "Kayra",
        "image": "https://i.scdn.co/image/ab67616d00001e020757d61990f017fcdcb4b538",
        "peak": "53",
        "prev": "53",
        "streak": "48",
        "streams": "168,277",
        "spotifyID": "2mgN0kh91PY3hlY88s3Zz5"
    },
    {
        "ranking": "58",
        "title": "I WANNA DANCE",
        "artist": "Batuflex, Ali471",
        "image": "https://i.scdn.co/image/ab67616d00001e02f1292187e19fb54701540181",
        "peak": "23",
        "prev": "62",
        "streak": "79",
        "streams": "161,179",
        "spotifyID": "2norl4Q0EjACN5kIshyP7k"
    },
    {
        "ranking": "59",
        "title": "Ki Sen",
        "artist": "Yalın",
        "image": "https://i.scdn.co/image/ab67616d00001e0270af0f9e8ab455f570baecf2",
        "peak": "48",
        "prev": "59",
        "streak": "110",
        "streams": "157,745",
        "spotifyID": "1HcbuJlFXlXaYw1S1M04KG"
    },
    {
        "ranking": "60",
        "title": "Olmazlara Vuruluyorum",
        "artist": "Mert Demir, Duygu Edis",
        "image": "https://i.scdn.co/image/ab67616d00001e02cc7a8305197dcedff3e2f3fb",
        "peak": "11",
        "prev": "63",
        "streak": "86",
        "streams": "156,313",
        "spotifyID": "72Zc1OvPqpZUqxArlAS0QW"
    },
    {
        "ranking": "61",
        "title": "Çek Kamaracı",
        "artist": "Şenol Evgi HD",
        "image": "https://i.scdn.co/image/ab67616d00001e020d31ab228b887f7d48982467",
        "peak": "51",
        "prev": "78",
        "streak": "75",
        "streams": "154,305",
        "spotifyID": "7oVfTik9UQxJAndLm3ZSQD"
    },
    {
        "ranking": "62",
        "title": "Her Nerdeysen",
        "artist": "Ati242",
        "image": "https://i.scdn.co/image/ab67616d00001e0279dbe6c33d218de4aa59223b",
        "peak": "19",
        "prev": "61",
        "streak": "30",
        "streams": "152,964",
        "spotifyID": "65txmqjijZoGYs1irX6tBU"
    },
    {
        "ranking": "63",
        "title": "Yetmedi",
        "artist": "Lvbel C5, AKDO",
        "image": "https://i.scdn.co/image/ab67616d00001e027b89f02ffd22e5964bbb8435",
        "peak": "10",
        "prev": "72",
        "streak": "100",
        "streams": "151,837",
        "spotifyID": "5TxqI3DLEbMVJkyVgentxd"
    },
    {
        "ranking": "64",
        "title": "ZEHİRLİ GÜL",
        "artist": "BLOK3",
        "image": "https://i.scdn.co/image/ab67616d00001e028f9028a4726d40fb8c8e0b44",
        "peak": "7",
        "prev": "65",
        "streak": "58",
        "streams": "150,463",
        "spotifyID": "0SwRpscOdj6PBhudNVIGpW"
    },
    {
        "ranking": "65",
        "title": "Aşk Nerden Nereye",
        "artist": "Gripin",
        "image": "https://i.scdn.co/image/ab67616d00001e023bb4426ccba314d34d5445b4",
        "peak": "54",
        "prev": "76",
        "streak": "287",
        "streams": "150,178",
        "spotifyID": "6vFHg6OAyhAWUbigiz3gn8"
    },
    {
        "ranking": "66",
        "title": "Böyle Sever",
        "artist": "Kahraman Deniz",
        "image": "https://i.scdn.co/image/ab67616d00001e025288becd356bc1ed97fbb1eb",
        "peak": "10",
        "prev": "71",
        "streak": "29",
        "streams": "149,151",
        "spotifyID": "7hU3H2id2pBVawD7e3zd8N"
    },
    {
        "ranking": "67",
        "title": "Yaralı",
        "artist": "Bengü",
        "image": "https://i.scdn.co/image/ab67616d00001e02889b7727078808c59beb764f",
        "peak": "55",
        "prev": "68",
        "streak": "28",
        "streams": "146,978",
        "spotifyID": "4KTeeyIWQTwXWI7hw0boRK"
    },
    {
        "ranking": "68",
        "title": "Gitme",
        "artist": "Dolu Kadehi Ters Tut, Sedef Sebüktekin",
        "image": "https://i.scdn.co/image/ab67616d00001e0261d6750a0251c9499570e586",
        "peak": "11",
        "prev": "80",
        "streak": "1946",
        "streams": "144,265",
        "spotifyID": "4Sng3wnol2Gb2yXgFdr9lj"
    },
    {
        "ranking": "69",
        "title": "Hüznü Hecem",
        "artist": "Yener Çevik",
        "image": "https://i.scdn.co/image/ab67616d00001e02d3da47e9ca7ba0e17f07c1f1",
        "peak": "28",
        "prev": "69",
        "streak": "259",
        "streams": "144,047",
        "spotifyID": "3OKCljxHDet7MaQ83o6l6s"
    },
    {
        "ranking": "70",
        "title": "Gel Bana",
        "artist": "Mustafa Sandal",
        "image": "https://i.scdn.co/image/ab67616d00001e02e2d1fad972e00d4c31c0a192",
        "peak": "6",
        "prev": "101",
        "streak": "204",
        "streams": "143,903",
        "spotifyID": "0vTv4JqDAjhix5KCUmJDou"
    },
    {
        "ranking": "71",
        "title": "Yara",
        "artist": "Kalben",
        "image": "https://i.scdn.co/image/ab67616d00001e024a55bde3a9ca9c2c68912956",
        "peak": "4",
        "prev": "75",
        "streak": "983",
        "streams": "143,707",
        "spotifyID": "1IquNFg2RRH1CLRAHNVgQ9"
    },
    {
        "ranking": "72",
        "title": "ELLERİM BOŞ",
        "artist": "M Lisa",
        "image": "https://i.scdn.co/image/ab67616d00001e026dce58d9992001a3d5d8916d",
        "peak": "25",
        "prev": "67",
        "streak": "420",
        "streams": "141,885",
        "spotifyID": "0Y4mwQ4z0Voplgh7o2OZYm"
    },
    {
        "ranking": "73",
        "title": "Mesela Yani",
        "artist": "Kayra",
        "image": "https://i.scdn.co/image/ab67616d00001e02d95da33d88c2b590329a8d66",
        "peak": "66",
        "prev": "74",
        "streak": "140",
        "streams": "140,249",
        "spotifyID": "6rDS12tA5szXrKyvL77wSb"
    },
    {
        "ranking": "74",
        "title": "Shoote Shoote",
        "artist": "Ati242",
        "image": "https://i.scdn.co/image/ab67616d00001e0231451e2675b8bbfecfed4e21",
        "peak": "39",
        "prev": "81",
        "streak": "156",
        "streams": "140,098",
        "spotifyID": "3miyN5Xj06i5cfy8vNZfDU"
    },
    {
        "ranking": "75",
        "title": "Die With A Smile",
        "artist": "Lady Gaga, Bruno Mars",
        "image": "https://i.scdn.co/image/ab67616d00001e0282ea2e9e1858aa012c57cd45",
        "peak": "67",
        "prev": "77",
        "streak": "55",
        "streams": "139,496",
        "spotifyID": "2plbrEY59IikOBgBGLjaoe"
    },
    {
        "ranking": "76",
        "title": "Altüst Olmuşum",
        "artist": "Mavi Gri",
        "image": "https://i.scdn.co/image/ab67616d00001e02fd348699521cceeffbf60fbc",
        "peak": "11",
        "prev": "82",
        "streak": "1155",
        "streams": "138,819",
        "spotifyID": "13THdxqHT11aSk3G8nUDzZ"
    },
    {
        "ranking": "77",
        "title": "Sahte Sonbahar",
        "artist": "Semicenk",
        "image": "https://i.scdn.co/image/ab67616d00001e02dc4721fefe12a86355da4fed",
        "peak": "12",
        "prev": "42",
        "streak": "93",
        "streams": "137,136",
        "spotifyID": "1ACI7zmoUY34xcrKrYeypb"
    },
    {
        "ranking": "78",
        "title": "Küçücüğüm",
        "artist": "Yalın",
        "image": "https://i.scdn.co/image/ab67616d00001e02c7e7617a47c1d76c37b00a88",
        "peak": "45",
        "prev": "100",
        "streak": "259",
        "streams": "136,846",
        "spotifyID": "1jhnbRVTmRJjnRhabesRqn"
    },
    {
        "ranking": "79",
        "title": "Yan Benimle",
        "artist": "Sıla",
        "image": "https://i.scdn.co/image/ab67616d00001e02259f95204897221b295a5641",
        "peak": "8",
        "prev": "186",
        "streak": "3",
        "streams": "136,656",
        "spotifyID": "2LX6XfSqCKBrt2qJngS87z"
    },
    {
        "ranking": "80",
        "title": "Sezen Aksu",
        "artist": "Lvbel C5",
        "image": "https://i.scdn.co/image/ab67616d00001e02bde27f666d136d4c7e6e71a9",
        "peak": "1",
        "prev": "109",
        "streak": "212",
        "streams": "135,940",
        "spotifyID": "0GuWyPyj4MVvT4qYsl6BOS"
    },
    {
        "ranking": "81",
        "title": "Acıtır gibi severek",
        "artist": "Canozan",
        "image": "https://i.scdn.co/image/ab67616d00001e0235d7a7df767f5bd84fb4cec3",
        "peak": "57",
        "prev": "60",
        "streak": "23",
        "streams": "134,377",
        "spotifyID": "4EC9KUi9fXKFzK17Or0A1a"
    },
    {
        "ranking": "82",
        "title": "Sana El Pençe Durmam",
        "artist": "Emre Fel",
        "image": "https://i.scdn.co/image/ab67616d00001e0243d6a282106606dad5557046",
        "peak": "4",
        "prev": "92",
        "streak": "173",
        "streams": "132,973",
        "spotifyID": "1cnx5g8kHElNAf28sV3mRJ"
    },
    {
        "ranking": "83",
        "title": "Bir Gün Ol Yerimde",
        "artist": "Doğu Swag, Aleyna Tilki",
        "image": "https://i.scdn.co/image/ab67616d00001e027dad70c3c0a9118d66ec4de7",
        "peak": "14",
        "prev": "70",
        "streak": "345",
        "streams": "132,359",
        "spotifyID": "4NYYwPTLIgoyPNG2iu3OrG"
    },
    {
        "ranking": "84",
        "title": "Sen Kaldın",
        "artist": "Semicenk",
        "image": "https://i.scdn.co/image/ab67616d00001e02dc4721fefe12a86355da4fed",
        "peak": "32",
        "prev": "73",
        "streak": "93",
        "streams": "131,988",
        "spotifyID": "0VOnehekjQz9cvUwLzmYSQ"
    },
    {
        "ranking": "85",
        "title": "Bir Derdim Var",
        "artist": "mor ve ötesi",
        "image": "https://i.scdn.co/image/ab67616d00001e0261cd6f5ad7c69b76adbc5419",
        "peak": "21",
        "prev": "95",
        "streak": "2686",
        "streams": "131,983",
        "spotifyID": "5UV2oqgMXvlkOvvtK3aT7f"
    },
    {
        "ranking": "86",
        "title": "Lan",
        "artist": "Zeynep Bastık",
        "image": "https://i.scdn.co/image/ab67616d00001e028e7b82d15a183fc2010b8183",
        "peak": "1",
        "prev": "89",
        "streak": "247",
        "streams": "131,975",
        "spotifyID": "1whKKdtCiFjN7MW7DrIRUH"
    },
    {
        "ranking": "87",
        "title": "Ben Sana Gelemem",
        "artist": "Mela Bedel",
        "image": "https://i.scdn.co/image/ab67616d00001e023e3ac35e4c3cac64613d509f",
        "peak": "6",
        "prev": "79",
        "streak": "212",
        "streams": "131,603",
        "spotifyID": "3gdY5WFt7i6BWVLie3t6hQ"
    },
    {
        "ranking": "88",
        "title": "LAF",
        "artist": "BLOK3",
        "image": "https://i.scdn.co/image/ab67616d00001e02ecb9ca081d6477ef50d6051b",
        "peak": "3",
        "prev": "87",
        "streak": "212",
        "streams": "131,158",
        "spotifyID": "7rHLpc3SZobYPDyBF06uok"
    },
    {
        "ranking": "89",
        "title": "HER YER FAVELA",
        "artist": "Critical, UZI, Heijan, Muti",
        "image": "https://i.scdn.co/image/ab67616d00001e02bde64a187cd5f52128634bce",
        "peak": "21",
        "prev": "85",
        "streak": "51",
        "streams": "128,689",
        "spotifyID": "5fuPdS5jBncmRu9uu1MLOr"
    },
    {
        "ranking": "90",
        "title": "Boş Yere - Lan ben sana nerden tutuldum",
        "artist": "Can Toğrulca",
        "image": "https://i.scdn.co/image/ab67616d00001e023695cd45b5c1abeda7deec86",
        "peak": "11",
        "prev": "86",
        "streak": "61",
        "streams": "127,463",
        "spotifyID": "1hlVcQCwARlFc8fqUb0Z01"
    },
    {
        "ranking": "91",
        "title": "Nilüfer",
        "artist": "Müslüm Gürses",
        "image": "https://i.scdn.co/image/ab67616d00001e02023db1018bba12eae732abac",
        "peak": "9",
        "prev": "106",
        "streak": "31",
        "streams": "126,228",
        "spotifyID": "4cHrCNJTdMfbtY0fjc5ged"
    },
    {
        "ranking": "92",
        "title": "Her şey Sensin",
        "artist": "Yalın",
        "image": "https://i.scdn.co/image/ab67616d00001e025a4f77cfbfe3c86dc0b3d32d",
        "peak": "63",
        "prev": "83",
        "streak": "105",
        "streams": "124,327",
        "spotifyID": "406NzjjqZlOiFyIvhTGcAQ"
    },
    {
        "ranking": "93",
        "title": "VUR",
        "artist": "BLOK3",
        "image": "https://i.scdn.co/image/ab67616d00001e021fc84480c30825a5b7fd549e",
        "peak": "5",
        "prev": "84",
        "streak": "40",
        "streams": "124,169",
        "spotifyID": "2Nt4eocAv9wi1vHshhSdpF"
    },
    {
        "ranking": "94",
        "title": "Ayrı Gitme",
        "artist": "Aleyna Tilki",
        "image": "https://i.scdn.co/image/ab67616d00001e02e0242dad9021163a6272e0c7",
        "peak": "26",
        "prev": "90",
        "streak": "122",
        "streams": "124,098",
        "spotifyID": "6dqkb11C20YDLZNhNAzWxz"
    },
    {
        "ranking": "95",
        "title": "Seni Dert Etmeler",
        "artist": "Madrigal",
        "image": "https://i.scdn.co/image/ab67616d00001e029aa96c06d5c346ccf6ffaf8d",
        "peak": "1",
        "prev": "88",
        "streak": "1661",
        "streams": "123,664",
        "spotifyID": "10n66m41IGjA2ZulKPK7Ew"
    },
    {
        "ranking": "96",
        "title": "Caney",
        "artist": "UZI, Azer Bülbül",
        "image": "https://i.scdn.co/image/ab67616d00001e0207b281bea5a321aa85d3e987",
        "peak": "2",
        "prev": "96",
        "streak": "514",
        "streams": "123,456",
        "spotifyID": "5mE8MWkWjLbfmd9ipiroVt"
    },
    {
        "ranking": "97",
        "title": "Kader Sağ Olsun",
        "artist": "Semicenk",
        "image": "https://i.scdn.co/image/ab67616d00001e02dc4721fefe12a86355da4fed",
        "peak": "1",
        "prev": "129",
        "streak": "93",
        "streams": "122,827",
        "spotifyID": "2crO2eSwgjOoAanagD2sFc"
    },
    {
        "ranking": "98",
        "title": "Med Cezir",
        "artist": "Ceza",
        "image": "https://i.scdn.co/image/19e6684f274833b0cd28f15a55e9edbfeb930240",
        "peak": "19",
        "prev": "98",
        "streak": "123",
        "streams": "122,577",
        "spotifyID": "4ktTv8OPQDbahR4opPanNq"
    },
    {
        "ranking": "99",
        "title": "Hoşçakal",
        "artist": "Ati242",
        "image": "https://i.scdn.co/image/ab67616d00001e0279dbe6c33d218de4aa59223b",
        "peak": "29",
        "prev": "94",
        "streak": "44",
        "streams": "122,441",
        "spotifyID": "1clLR0ZWsPijZZ8PvAJyi2"
    },
    {
        "ranking": "100",
        "title": "BAYBAY",
        "artist": "BLOK3",
        "image": "https://i.scdn.co/image/ab67616d00001e02b72937f282a7ae43e04c57ac",
        "peak": "3",
        "prev": "91",
        "streak": "604",
        "streams": "121,986",
        "spotifyID": "232LbugfZaCUwq82xiELtd"
    }
]